FTPflow/__init__.py
FTPflow/checkplatform.py
FTPflow/main_walker.py
FTPflow/runwalker.py
FTPflow/test.py
FTPflow/traverse.py
FTPflow/walker.py
FTPflow/daemons/__init__.py
FTPflow/daemons/unixdaemon.py
FTPflow/daemons/windaemon.py
FTPflow/daemons/winservice.py
FTPflow-0.5.dist-info/DESCRIPTION.rst
FTPflow-0.5.dist-info/METADATA
FTPflow-0.5.dist-info/RECORD
FTPflow-0.5.dist-info/WHEEL
FTPflow-0.5.dist-info/metadata.json
FTPflow-0.5.dist-info/top_level.txt
