Metadata-Version: 2.0
Name: FTPflow
Version: 0.5
Summary: Optimally traversing extremely large FTP directory trees.
Home-page: https://github.com/airportbio/FTPflow
Author: Kasra Vand, Bohdan Khomtchouk
Author-email: bohdan@stanford.edu, kasraavand@gmail.com
License: UNKNOWN
Keywords: FTP,traverse,directory tree,optimized
Platform: UNKNOWN
